AUTHORS.rst
CONTRIBUTING.rst
HISTORY.rst
LICENSE
MANIFEST.in
README.rst
setup.cfg
setup.py
couchdb_download_token/__init__.py
couchdb_download_token/config.py
couchdb_download_token/couchdb_download_token.py
couchdb_download_token/helpers.py
couchdb_download_token.egg-info/PKG-INFO
couchdb_download_token.egg-info/SOURCES.txt
couchdb_download_token.egg-info/dependency_links.txt
couchdb_download_token.egg-info/not-zip-safe
couchdb_download_token.egg-info/requires.txt
couchdb_download_token.egg-info/top_level.txt
docs/Makefile
docs/authors.rst
docs/conf.py
docs/configuration.rst
docs/contributing.rst
docs/couchdb_download_token.rst
docs/history.rst
docs/index.rst
docs/installation.rst
docs/make.bat
docs/modules.rst
docs/readme.rst
docs/usage.rst
docs/_build/html/_static/ajax-loader.gif
docs/_build/html/_static/comment-bright.png
docs/_build/html/_static/comment-close.png
docs/_build/html/_static/comment.png
docs/_build/html/_static/down-pressed.png
docs/_build/html/_static/down.png
docs/_build/html/_static/file.png
docs/_build/html/_static/minus.png
docs/_build/html/_static/plus.png
docs/_build/html/_static/up-pressed.png
docs/_build/html/_static/up.png
tests/__init__.py
tests/helpers.py
tests/test_download_endpoint.py
tests/test_helpers.py