Metadata-Version: 1.1
Name: couchdb-download-token
Version: 0.1.1
Summary: Simple web service that allows downloading CouchDB document attachments with a per-document download token.
Home-page: https://github.com/sh4r3m4n/couchdb_download_token
Author: Matías Lang
Author-email: yo@matiaslang.me
License: GNU General Public License v3
Keywords: couchdb_download_token
Platform: UNKNOWN
Classifier: Development Status :: 2 - Pre-Alpha
Classifier: Intended Audience :: Developers
Classifier: Natural Language :: English
Classifier: Programming Language :: Python :: 2
Classifier: Programming Language :: Python :: 2.6
Classifier: Programming Language :: Python :: 2.7
Classifier: Programming Language :: Python :: 3
Classifier: Programming Language :: Python :: 3.3
Classifier: Programming Language :: Python :: 3.4
Classifier: Programming Language :: Python :: 3.5
